pixelmatch/__init__.py
pixelmatch/contrib/__init__.py
pixelmatch/contrib/PIL.py
pixelmatch/core.py
pixelmatch/py.typed
pixelmatch/types.py
pixelmatch/utils.py
pixelmatch-0.2.4.dist-info/LICENSE
pixelmatch-0.2.4.dist-info/WHEEL
pixelmatch-0.2.4.dist-info/METADATA
pixelmatch-0.2.4.dist-info/RECORD
