Metadata-Version: 2.1
Name: pixelmatch
Version: 0.2.4
Summary: A pixel-level image comparison library.
Home-page: https://github.com/whtsky/pixelmatch-py
License: ISC
Author: Wu Haotian
Author-email: whtsky@gmail.com
Requires-Python: >=3.6.2,<4.0.0
Classifier: License :: OSI Approved
Classifier: Programming Language :: Python :: 3
Classifier: Programming Language :: Python :: 3.7
Classifier: Programming Language :: Python :: 3.8
Classifier: Programming Language :: Python :: 3.9
Project-URL: Repository, https://github.com/whtsky/pixelmatch-py
